spinn_machine/__init__.py
spinn_machine/_version.py
spinn_machine/chip.py
spinn_machine/config_setup.py
spinn_machine/core_subset.py
spinn_machine/core_subsets.py
spinn_machine/exceptions.py
spinn_machine/frozen_core_subsets.py
spinn_machine/full_wrap_machine.py
spinn_machine/horizontal_wrap_machine.py
spinn_machine/json_machine.py
spinn_machine/link.py
spinn_machine/machine.py
spinn_machine/machine_factory.py
spinn_machine/multicast_routing_entry.py
spinn_machine/no_wrap_machine.py
spinn_machine/py.typed
spinn_machine/router.py
spinn_machine/routing_entry.py
spinn_machine/spinn_machine.cfg
spinn_machine/spinnaker_triad_geometry.py
spinn_machine/vertical_wrap_machine.py
spinn_machine/virtual_machine.py
spinn_machine/data/__init__.py
spinn_machine/data/machine_data_view.py
spinn_machine/data/machine_data_writer.py
spinn_machine/ignores/__init__.py
spinn_machine/ignores/ignore_chip.py
spinn_machine/ignores/ignore_core.py
spinn_machine/ignores/ignore_link.py
spinn_machine/link_data_objects/__init__.py
spinn_machine/link_data_objects/abstract_link_data.py
spinn_machine/link_data_objects/fpga_link_data.py
spinn_machine/link_data_objects/spinnaker_link_data.py
spinn_machine/spalloc_server/__init__.py
spinn_machine/spalloc_server/configuration.py
spinn_machine/spalloc_server/coordinates.py
spinn_machine/spalloc_server/links.py
spinn_machine/spalloc_server/py2json.py
spinn_machine/tags/__init__.py
spinn_machine/tags/abstract_tag.py
spinn_machine/tags/iptag.py
spinn_machine/tags/reverse_iptag.py
spinn_machine/version/__init__.py
spinn_machine/version/abstract_version.py
spinn_machine/version/vec2mesh_reader.py
spinn_machine/version/version_201.py
spinn_machine/version/version_248.py
spinn_machine/version/version_3.py
spinn_machine/version/version_48_chips.py
spinn_machine/version/version_5.py
spinn_machine/version/version_factory.py
spinn_machine/version/version_spin1.py
spinn_machine/version/version_spin2.py
spinn_machine/version/version_strings.py
spinnmachine-1!7.4.0.dist-info/licenses/LICENSE
spinnmachine-1!7.4.0.dist-info/licenses/LICENSE_POLICY.md
spinnmachine-1!7.4.0.dist-info/METADATA
spinnmachine-1!7.4.0.dist-info/WHEEL
spinnmachine-1!7.4.0.dist-info/top_level.txt
spinnmachine-1!7.4.0.dist-info/zip-safe
spinnmachine-1!7.4.0.dist-info/RECORD
